kuavo_humanoid_sdk/__init__.py
kuavo_humanoid_sdk/common/logger.py
kuavo_humanoid_sdk/interfaces/__init__.py
kuavo_humanoid_sdk/interfaces/data_types.py
kuavo_humanoid_sdk/interfaces/end_effector.py
kuavo_humanoid_sdk/interfaces/robot.py
kuavo_humanoid_sdk/interfaces/robot_info.py
kuavo_humanoid_sdk/kuavo/__init__.py
kuavo_humanoid_sdk/kuavo/dexterous_hand.py
kuavo_humanoid_sdk/kuavo/leju_claw.py
kuavo_humanoid_sdk/kuavo/robot.py
kuavo_humanoid_sdk/kuavo/robot_arm.py
kuavo_humanoid_sdk/kuavo/robot_head.py
kuavo_humanoid_sdk/kuavo/robot_info.py
kuavo_humanoid_sdk/kuavo/robot_state.py
kuavo_humanoid_sdk/kuavo/core/core.py
kuavo_humanoid_sdk/kuavo/core/dex_hand_control.py
kuavo_humanoid_sdk/kuavo/core/leju_claw_control.py
kuavo_humanoid_sdk/kuavo/core/ros_env.py
kuavo_humanoid_sdk/kuavo/core/ros/control.py
kuavo_humanoid_sdk/kuavo/core/ros/param.py
kuavo_humanoid_sdk/kuavo/core/ros/sat_utils.py
kuavo_humanoid_sdk/kuavo/core/ros/state.py
ohh_test_sdk-0.1.0.dist-info/METADATA
ohh_test_sdk-0.1.0.dist-info/WHEEL
ohh_test_sdk-0.1.0.dist-info/top_level.txt
ohh_test_sdk-0.1.0.dist-info/RECORD
